{"meta":{"type":"db","canSave":true,"canEdit":true,"canStar":true,"slug":"storagegrid-webscale","expires":"0001-01-01T00:00:00Z","created":"2016-02-03T15:20:36Z","updated":"2016-03-02T09:37:31Z"},"dashboard":{"annotations":{"list":[]},"editable":true,"hideControls":false,"id":1,"links":[],"originalTitle":"StorageGRID Webscale","refresh":false,"rows":[{"collapse":false,"editable":true,"height":"250px","panels":[{"aliasColors":{},"bars":false,"datasource":"elasticsearch","editable":true,"error":false,"fill":1,"grid":{"leftLogBase":1,"leftMax":null,"leftMin":null,"rightLogBase":1,"rightMax":null,"rightMin":null,"threshold1":null,"threshold1Color":"rgba(216, 200, 27, 0.27)","threshold2":null,"threshold2Color":"rgba(234, 112, 112, 0.22)"},"id":4,"isNew":true,"leftYAxisLabel":"Operations/Minute","legend":{"alignAsTable":true,"avg":true,"current":false,"hideEmpty":false,"max":true,"min":true,"rightSide":false,"show":true,"total":false,"values":true},"lines":true,"linewidth":2,"links":[],"nullPointMode":"null as zero","percentage":false,"pointradius":5,"points":false,"renderer":"flot","rightYAxisLabel":"Operation Duration","seriesOverrides":[{"alias":"Average Time per Operation","yaxis":2},{"alias":"Operations per Minute","bars":true,"lines":false}],"span":12,"stack":false,"steppedLine":false,"targets":[{"alias":"Operations per Minute","bucketAggs":[{"field":"@timestamp","id":"2","settings":{"interval":"1m","min_doc_count":0},"type":"date_histogram"}],"dsType":"elasticsearch","metrics":[{"field":"select field","id":"1","type":"count"}],"refId":"A","timeField":"@timestamp"},{"alias":"Average Time per Operation","bucketAggs":[{"field":"@timestamp","id":"2","settings":{"interval":"1m","min_doc_count":0},"type":"date_histogram"}],"dsType":"elasticsearch","metrics":[{"field":"TIME(UI64)","id":"1","meta":{},"settings":{},"type":"avg"}],"refId":"B","timeField":"@timestamp"}],"timeFrom":null,"timeShift":null,"title":"StorageGRID Operation Overview","tooltip":{"shared":true,"value_type":"cumulative"},"type":"graph","x-axis":true,"y-axis":true,"y_formats":["short","µs"]}],"title":"New row"},{"collapse":false,"editable":true,"height":"250px","panels":[{"aliasColors":{},"bars":true,"datasource":"elasticsearch","editable":true,"error":false,"fill":1,"grid":{"leftLogBase":1,"leftMax":null,"leftMin":null,"rightLogBase":1,"rightMax":null,"rightMin":null,"threshold1":null,"threshold1Color":"rgba(216, 200, 27, 0.27)","threshold2":null,"threshold2Color":"rgba(234, 112, 112, 0.22)"},"id":1,"isNew":true,"leftYAxisLabel":"Ops/min","legend":{"alignAsTable":true,"avg":true,"current":false,"max":true,"min":true,"rightSide":true,"show":true,"total":false,"values":true},"lines":false,"linewidth":2,"links":[],"nullPointMode":"null","percentage":false,"pointradius":5,"points":false,"renderer":"flot","rightYAxisLabel":"","seriesOverrides":[],"span":6,"stack":true,"steppedLine":false,"targets":[{"alias":"GET","bucketAggs":[{"field":"@timestamp","id":"2","settings":{"interval":"1m","min_doc_count":0},"type":"date_histogram"}],"dsType":"elasticsearch","hide":false,"metrics":[{"field":"TYP","id":"1","meta":{},"settings":{},"type":"count"}],"query":"ATYP\\(FC32\\):SGET AND _exists_:S3KY\\(CSTR\\)","refId":"A","timeField":"@timestamp"},{"alias":"LIST","bucketAggs":[{"field":"@timestamp","id":"2","settings":{"interval":"1m","min_doc_count":0},"type":"date_histogram"}],"dsType":"elasticsearch","metrics":[{"field":"select field","id":"1","type":"count"}],"query":"ATYP\\(FC32\\):SGET AND _missing_:S3KY\\(CSTR\\)","refId":"D","timeField":"@timestamp"},{"alias":"PUT","bucketAggs":[{"field":"@timestamp","id":"2","settings":{"interval":"1m","min_doc_count":0},"type":"date_histogram"}],"dsType":"elasticsearch","metrics":[{"field":"select field","id":"1","type":"count"}],"query":"ATYP\\(FC32\\):SPUT","refId":"B","timeField":"@timestamp"},{"alias":"DEL","bucketAggs":[{"field":"@timestamp","id":"2","settings":{"interval":"1m","min_doc_count":0},"type":"date_histogram"}],"dsType":"elasticsearch","metrics":[{"field":"select field","id":"1","type":"count"}],"query":"ATYP\\(FC32\\):SDEL","refId":"C","timeField":"@timestamp"}],"timeFrom":null,"timeShift":null,"title":"S3 Operation Distribution","tooltip":{"shared":true,"value_type":"cumulative"},"type":"graph","x-axis":true,"y-axis":true,"y_formats":["none","short"]},{"aliasColors":{},"bars":false,"datasource":"elasticsearch","editable":true,"error":false,"fill":1,"grid":{"leftLogBase":1,"leftMax":null,"leftMin":null,"rightLogBase":1,"rightMax":null,"rightMin":null,"threshold1":null,"threshold1Color":"rgba(216, 200, 27, 0.27)","threshold2":null,"threshold2Color":"rgba(234, 112, 112, 0.22)"},"id":6,"isNew":true,"leftYAxisLabel":"Ops/Min","legend":{"alignAsTable":true,"avg":true,"current":false,"max":true,"min":false,"rightSide":false,"show":true,"total":false,"values":true},"lines":true,"linewidth":2,"links":[],"nullPointMode":"null as zero","percentage":false,"pointradius":5,"points":false,"renderer":"flot","rightYAxisLabel":"","seriesOverrides":[],"span":6,"stack":false,"steppedLine":false,"targets":[{"alias":"S3 GET Ops/min","bucketAggs":[{"field":"@timestamp","id":"2","settings":{"interval":"1m","min_doc_count":0},"type":"date_histogram"}],"dsType":"elasticsearch","metrics":[{"field":"select field","id":"1","type":"count"}],"query":"ATYP\\(FC32\\):SGET AND _exists_:S3KY\\(CSTR\\)","refId":"A","timeField":"@timestamp"},{"alias":"S3 PUT Ops/min","bucketAggs":[{"field":"@timestamp","id":"2","settings":{"interval":"1m","min_doc_count":0},"type":"date_histogram"}],"dsType":"elasticsearch","hide":false,"metrics":[{"field":"CSIZ(UI64)","id":"1","meta":{},"settings":{},"type":"count"}],"query":"ATYP\\(FC32\\):SPUT AND _exists_:S3KY\\(CSTR\\)","refId":"B","timeField":"@timestamp"}],"timeFrom":null,"timeShift":null,"title":"S3 Ops per Minute","tooltip":{"shared":true,"value_type":"cumulative"},"transparent":false,"type":"graph","x-axis":true,"y-axis":true,"y_formats":["none","none"]}],"showTitle":true,"title":"S3 Performance Metrics"},{"collapse":false,"editable":true,"height":"250px","panels":[{"aliasColors":{},"bars":false,"datasource":"elasticsearch","editable":true,"error":false,"fill":1,"grid":{"leftLogBase":1,"leftMax":null,"leftMin":0,"rightLogBase":1,"rightMax":null,"rightMin":0,"threshold1":null,"threshold1Color":"rgba(216, 200, 27, 0.27)","threshold2":null,"threshold2Color":"rgba(234, 112, 112, 0.22)"},"id":8,"isNew":true,"leftYAxisLabel":"","legend":{"alignAsTable":true,"avg":true,"current":false,"max":true,"min":true,"rightSide":false,"show":true,"total":false,"values":true},"lines":true,"linewidth":2,"links":[],"nullPointMode":"connected","percentage":false,"pointradius":5,"points":false,"renderer":"flot","seriesOverrides":[],"span":4,"stack":false,"steppedLine":false,"targets":[{"alias":"Avg GET Processing time","bucketAggs":[{"field":"@timestamp","id":"2","settings":{"interval":"1m","min_doc_count":0},"type":"date_histogram"}],"dsType":"elasticsearch","metrics":[{"field":"TIME(UI64)","id":"1","inlineScript":null,"meta":{},"settings":{},"type":"avg"}],"query":"ATYP\\(FC32\\):SGET AND _exists_:S3KY\\(CSTR\\)","refId":"A","timeField":"@timestamp"}],"timeFrom":null,"timeShift":null,"title":"Avg GET processing time","tooltip":{"shared":true,"value_type":"cumulative"},"type":"graph","x-axis":true,"y-axis":true,"y_formats":["µs","short"]},{"aliasColors":{},"bars":false,"datasource":"elasticsearch","editable":true,"error":false,"fill":1,"grid":{"leftLogBase":1,"leftMax":null,"leftMin":0,"rightLogBase":1,"rightMax":null,"rightMin":0,"threshold1":null,"threshold1Color":"rgba(216, 200, 27, 0.27)","threshold2":null,"threshold2Color":"rgba(234, 112, 112, 0.22)"},"id":10,"isNew":true,"leftYAxisLabel":"","legend":{"alignAsTable":true,"avg":true,"current":false,"max":true,"min":true,"rightSide":false,"show":true,"total":false,"values":true},"lines":true,"linewidth":2,"links":[],"nullPointMode":"connected","percentage":false,"pointradius":5,"points":false,"renderer":"flot","seriesOverrides":[],"span":4,"stack":false,"steppedLine":false,"targets":[{"alias":"Avg PUT Processing time","bucketAggs":[{"field":"@timestamp","id":"2","settings":{"interval":"1m","min_doc_count":0},"type":"date_histogram"}],"dsType":"elasticsearch","metrics":[{"field":"TIME(UI64)","id":"1","meta":{},"settings":{},"type":"avg"}],"query":"ATYP\\(FC32\\):SPUT","refId":"B","timeField":"@timestamp"}],"timeFrom":null,"timeShift":null,"title":"Avg PUT processing time","tooltip":{"shared":true,"value_type":"cumulative"},"type":"graph","x-axis":true,"y-axis":true,"y_formats":["µs","short"]},{"aliasColors":{},"bars":false,"datasource":"elasticsearch","editable":true,"error":false,"fill":1,"grid":{"leftLogBase":1,"leftMax":null,"leftMin":null,"rightLogBase":1,"rightMax":null,"rightMin":null,"threshold1":null,"threshold1Color":"rgba(216, 200, 27, 0.27)","threshold2":null,"threshold2Color":"rgba(234, 112, 112, 0.22)"},"id":5,"isNew":true,"leftYAxisLabel":"Avg Object Size","legend":{"alignAsTable":true,"avg":true,"current":false,"max":true,"min":false,"show":true,"total":false,"values":true},"lines":true,"linewidth":2,"links":[],"nullPointMode":"null as zero","percentage":false,"pointradius":5,"points":false,"renderer":"flot","rightYAxisLabel":"","seriesOverrides":[],"span":4,"stack":false,"steppedLine":false,"targets":[{"alias":"S3 GET Avg Object Size","bucketAggs":[{"field":"@timestamp","id":"2","settings":{"interval":"1m","min_doc_count":0},"type":"date_histogram"}],"dsType":"elasticsearch","metrics":[{"field":"CSIZ(UI64)","id":"1","meta":{},"settings":{},"type":"avg"}],"query":"ATYP\\(FC32\\):SGET","refId":"A","timeField":"@timestamp"},{"alias":"S3 PUT Avg Object Size","bucketAggs":[{"field":"@timestamp","id":"2","settings":{"interval":"1m","min_doc_count":0},"type":"date_histogram"}],"dsType":"elasticsearch","metrics":[{"field":"CSIZ(UI64)","id":"1","meta":{},"settings":{},"type":"avg"}],"query":"ATYP\\(FC32\\):SPUT","refId":"B","timeField":"@timestamp"}],"timeFrom":null,"timeShift":null,"title":"S3 Avg Object Size","tooltip":{"shared":true,"value_type":"cumulative"},"type":"graph","x-axis":true,"y-axis":true,"y_formats":["bytes","none"]}],"showTitle":true,"title":"S3 Details"}],"schemaVersion":8,"sharedCrosshair":false,"style":"dark","tags":[],"templating":{"list":[]},"time":{"from":"now-1h","to":"now"},"timepicker":{"now":true,"refresh_intervals":["5s","10s","30s","1m","5m","15m","30m","1h","2h","1d"],"time_options":["5m","15m","1h","6h","12h","24h","2d","7d","30d"]},"timezone":"browser","title":"StorageGRID Webscale","version":9}}